[
  {
    "StudentNo": 2016217001,
    "Name": "Esra",
    "Surname": "GUVEN",
    "DepartmentNo": 2016217
  },
  {
    "StudentNo": 2016217002,
    "Name": "Funda",
    "Surname": "TULAY",
    "DepartmentNo": 2016217
  },
  {
    "StudentNo": 2016217003,
    "Name": "Bilal",
    "Surname": "OZTURK",
    "DepartmentNo": 2016217
  },
  {
    "StudentNo": 2016217004,
    "Name": "Funda",
    "Surname": "GUVEN",
    "DepartmentNo": 2016217
  },
  {
    "StudentNo": 2016217005,
    "Name": "Berika",
    "Surname": "KOC",
    "DepartmentNo": 2016217
  },
  {
    "StudentNo": 2016217006,
    "Name": "Arda",
    "Surname": "OZTURK",
    "DepartmentNo": 2016217
  },
  {
    "StudentNo": 2016217007,
    "Name": "Leyla",
    "Surname": "KOC",
    "DepartmentNo": 2016217
  },
  {
    "StudentNo": 2016217008,
    "Name": "Mustafa",
    "Surname": "CELIK",
    "DepartmentNo": 2016217
  },
  {
    "StudentNo": 2016217009,
    "Name": "Emine",
    "Surname": "DOR",
    "DepartmentNo": 2016217
  },
  {
    "StudentNo": 2016217010,
    "Name": "Halis",
    "Surname": "CELIK",
    "DepartmentNo": 2016217
  },
  {
    "StudentNo": 2016217011,
    "Name": "Ali",
    "Surname": "DEMIR",
    "DepartmentNo": 2016217
  },
  {
    "StudentNo": 2016217012,
    "Name": "Leyla",
    "Surname": "SANIYE",
    "DepartmentNo": 2016217
  },
  {
    "StudentNo": 2016217013,
    "Name": "Arif",
    "Surname": "GUVEN",
    "DepartmentNo": 2016217
  },
  {
    "StudentNo": 2016217014,
    "Name": "Emine",
    "Surname": "CELIK",
    "DepartmentNo": 2016217
  },
  {
    "StudentNo": 2016217015,
    "Name": "Halis",
    "Surname": "DOR",
    "DepartmentNo": 2016217
  }
]